{
  "players": {
    "MACDOUKEN": {
      "name": "MACDOUKEN",
      "clubTag": "BYTE",
      "stats": {
        "totalPoints": 30507,
        "cupsPlayed": 23,
        "wins": 2,
        "podiums": 8,
        "avgPosition": 4.52,
        "bestPosition": 1,
        "worstPosition": 8
      },
      "bestTimes": [
        {
          "cupId": 1,
          "time": "0:37.667",
          "date": "30.10.2024"
        },
        {
          "cupId": 23,
          "time": "0:43.228",
          "date": "25.03.2026"
        }
      ],
      "cupHistory": [
        {
          "cupId": 1,
          "position": 1,
          "points": 1420
        },
        {
          "cupId": 2,
          "position": 3,
          "points": 1420
        },
        {
          "cupId": 3,
          "position": 7,
          "points": 1050
        },
        {
          "cupId": 4,
          "position": 6,
          "points": 1300
        },
        {
          "cupId": 5,
          "position": 8,
          "points": 1280
        },
        {
          "cupId": 7,
          "position": 6,
          "points": 1180
        },
        {
          "cupId": 8,
          "position": 6,
          "points": 1380
        },
        {
          "cupId": 9,
          "position": 3,
          "points": 1420
        },
        {
          "cupId": 10,
          "position": 4,
          "points": 1420
        },
        {
          "cupId": 11,
          "position": 2,
          "points": 1420
        },
        {
          "cupId": 13,
          "position": 6,
          "points": 1150
        },
        {
          "cupId": 14,
          "position": 1,
          "points": 1420
        },
        {
          "cupId": 15,
          "position": 3,
          "points": 1420
        },
        {
          "cupId": 16,
          "position": 3,
          "points": 1420
        },
        {
          "cupId": 17,
          "position": 6,
          "points": 1280
        },
        {
          "cupId": 18,
          "position": 5,
          "points": 1350
        },
        {
          "cupId": 19,
          "position": 4,
          "points": 1420
        },
        {
          "cupId": 20,
          "position": 6,
          "points": 1360
        },
        {
          "cupId": 21,
          "position": 6,
          "points": 1155
        },
        {
          "cupId": 22,
          "position": 7,
          "points": 982
        },
        {
          "cupId": 23,
          "position": 4,
          "points": 1420
        },
        {
          "cupId": 24,
          "position": 3,
          "points": 1420
        },
        {
          "cupId": 25,
          "position": 4,
          "points": 1420
        }
      ]
    },
    "HUEBSCH_AF": {
      "name": "HUEBSCH_AF",
      "clubTag": "WPT",
      "stats": {
        "totalPoints": 28940,
        "cupsPlayed": 21,
        "wins": 4,
        "podiums": 15,
        "avgPosition": 2.86,
        "bestPosition": 1,
        "worstPosition": 9
      },
      "bestTimes": [
        {
          "cupId": 2,
          "time": "0:45.101",
          "date": "06.11.2024"
        },
        {
          "cupId": 15,
          "time": "0:39.521",
          "date": "21.01.2026"
        }
      ],
      "cupHistory": [
        {
          "cupId": 1,
          "position": 2,
          "points": 1420
        },
        {
          "cupId": 2,
          "position": 1,
          "points": 1420
        },
        {
          "cupId": 4,
          "position": 2,
          "points": 1420
        },
        {
          "cupId": 5,
          "position": 2,
          "points": 1420
        },
        {
          "cupId": 8,
          "position": 5,
          "points": 1380
        },
        {
          "cupId": 9,
          "position": 4,
          "points": 1420
        },
        {
          "cupId": 10,
          "position": 2,
          "points": 1420
        },
        {
          "cupId": 11,
          "position": 3,
          "points": 1420
        },
        {
          "cupId": 12,
          "position": 2,
          "points": 1420
        },
        {
          "cupId": 13,
          "position": 2,
          "points": 1420
        },
        {
          "cupId": 14,
          "position": 9,
          "points": 580
        },
        {
          "cupId": 15,
          "position": 1,
          "points": 1420
        },
        {
          "cupId": 16,
          "position": 4,
          "points": 1420
        },
        {
          "cupId": 17,
          "position": 1,
          "points": 1420
        },
        {
          "cupId": 18,
          "position": 1,
          "points": 1420
        },
        {
          "cupId": 19,
          "position": 2,
          "points": 1420
        },
        {
          "cupId": 20,
          "position": 3,
          "points": 1420
        },
        {
          "cupId": 22,
          "position": 2,
          "points": 1420
        },
        {
          "cupId": 23,
          "position": 5,
          "points": 1420
        },
        {
          "cupId": 24,
          "position": 5,
          "points": 1420
        },
        {
          "cupId": 25,
          "position": 2,
          "points": 1420
        }
      ]
    },
    "FAILLORDXD": {
      "name": "FAILLORDXD",
      "clubTag": "BYTE",
      "stats": {
        "totalPoints": 23258,
        "cupsPlayed": 19,
        "wins": 1,
        "podiums": 4,
        "avgPosition": 5.32,
        "bestPosition": 1,
        "worstPosition": 10
      },
      "bestTimes": [
        {
          "cupId": 9,
          "time": "0:43.856",
          "date": "25.12.2024"
        },
        {
          "cupId": 10,
          "time": "0:50.524",
          "date": "01.01.2025"
        },
        {
          "cupId": 14,
          "time": "1:11.869",
          "date": "14.01.2026"
        }
      ],
      "cupHistory": [
        {
          "cupId": 1,
          "position": 3,
          "points": 1420
        },
        {
          "cupId": 2,
          "position": 4,
          "points": 1400
        },
        {
          "cupId": 3,
          "position": 8,
          "points": 980
        },
        {
          "cupId": 4,
          "position": 4,
          "points": 1380
        },
        {
          "cupId": 5,
          "position": 4,
          "points": 1380
        },
        {
          "cupId": 7,
          "position": 8,
          "points": 1070
        },
        {
          "cupId": 9,
          "position": 2,
          "points": 1420
        },
        {
          "cupId": 10,
          "position": 1,
          "points": 1420
        },
        {
          "cupId": 11,
          "position": 5,
          "points": 1420
        },
        {
          "cupId": 13,
          "position": 7,
          "points": 1110
        },
        {
          "cupId": 14,
          "position": 6,
          "points": 1270
        },
        {
          "cupId": 16,
          "position": 7,
          "points": 540
        },
        {
          "cupId": 17,
          "position": 7,
          "points": 1140
        },
        {
          "cupId": 18,
          "position": 4,
          "points": 1420
        },
        {
          "cupId": 19,
          "position": 3,
          "points": 1420
        },
        {
          "cupId": 20,
          "position": 5,
          "points": 1420
        },
        {
          "cupId": 21,
          "position": 10,
          "points": 889
        },
        {
          "cupId": 22,
          "position": 9,
          "points": 739
        },
        {
          "cupId": 24,
          "position": 4,
          "points": 1420
        }
      ]
    },
    "TEQAL-TM": {
      "name": "TEQAL-TM",
      "clubTag": "STWA",
      "stats": {
        "totalPoints": 9886,
        "cupsPlayed": 9,
        "wins": 1,
        "podiums": 3,
        "avgPosition": 5.67,
        "bestPosition": 1,
        "worstPosition": 14
      },
      "bestTimes": [],
      "cupHistory": [
        {
          "cupId": 1,
          "position": 4,
          "points": 1390
        },
        {
          "cupId": 2,
          "position": 10,
          "points": 390
        },
        {
          "cupId": 5,
          "position": 3,
          "points": 1420
        },
        {
          "cupId": 8,
          "position": 1,
          "points": 1420
        },
        {
          "cupId": 15,
          "position": 4,
          "points": 1420
        },
        {
          "cupId": 16,
          "position": 2,
          "points": 1420
        },
        {
          "cupId": 22,
          "position": 5,
          "points": 1226
        },
        {
          "cupId": 24,
          "position": 14,
          "points": 210
        },
        {
          "cupId": 25,
          "position": 8,
          "points": 990
        }
      ]
    },
    "BRATHERING_TM": {
      "name": "BRATHERING_TM",
      "clubTag": "STWA",
      "stats": {
        "totalPoints": 16627,
        "cupsPlayed": 17,
        "wins": 0,
        "podiums": 0,
        "avgPosition": 7.76,
        "bestPosition": 4,
        "worstPosition": 17
      },
      "bestTimes": [],
      "cupHistory": [
        {
          "cupId": 1,
          "position": 5,
          "points": 1370
        },
        {
          "cupId": 2,
          "position": 8,
          "points": 1010
        },
        {
          "cupId": 3,
          "position": 5,
          "points": 1320
        },
        {
          "cupId": 4,
          "position": 5,
          "points": 1350
        },
        {
          "cupId": 5,
          "position": 7,
          "points": 1290
        },
        {
          "cupId": 7,
          "position": 4,
          "points": 1390
        },
        {
          "cupId": 10,
          "position": 5,
          "points": 1420
        },
        {
          "cupId": 13,
          "position": 4,
          "points": 1420
        },
        {
          "cupId": 14,
          "position": 12,
          "points": 130
        },
        {
          "cupId": 16,
          "position": 8,
          "points": 400
        },
        {
          "cupId": 17,
          "position": 12,
          "points": 60
        },
        {
          "cupId": 19,
          "position": 5,
          "points": 1420
        },
        {
          "cupId": 21,
          "position": 8,
          "points": 1020
        },
        {
          "cupId": 22,
          "position": 8,
          "points": 964
        },
        {
          "cupId": 23,
          "position": 12,
          "points": 891
        },
        {
          "cupId": 24,
          "position": 17,
          "points": 20
        },
        {
          "cupId": 25,
          "position": 7,
          "points": 1152
        }
      ]
    },
    "CHRISHANX": {
      "name": "CHRISHANX",
      "clubTag": "BYTE",
      "stats": {
        "totalPoints": 1360,
        "cupsPlayed": 1,
        "wins": 0,
        "podiums": 0,
        "avgPosition": 6,
        "bestPosition": 6,
        "worstPosition": 6
      },
      "bestTimes": [],
      "cupHistory": [
        {
          "cupId": 1,
          "position": 6,
          "points": 1360
        }
      ]
    },
    "CONSPIRIA": {
      "name": "CONSPIRIA",
      "clubTag": "BYTE",
      "stats": {
        "totalPoints": 28221,
        "cupsPlayed": 22,
        "wins": 1,
        "podiums": 3,
        "avgPosition": 5.68,
        "bestPosition": 1,
        "worstPosition": 10
      },
      "bestTimes": [],
      "cupHistory": [
        {
          "cupId": 1,
          "position": 7,
          "points": 1310
        },
        {
          "cupId": 2,
          "position": 6,
          "points": 1360
        },
        {
          "cupId": 3,
          "position": 10,
          "points": 890
        },
        {
          "cupId": 4,
          "position": 3,
          "points": 1420
        },
        {
          "cupId": 5,
          "position": 5,
          "points": 1340
        },
        {
          "cupId": 7,
          "position": 5,
          "points": 1310
        },
        {
          "cupId": 8,
          "position": 4,
          "points": 1400
        },
        {
          "cupId": 9,
          "position": 7,
          "points": 930
        },
        {
          "cupId": 10,
          "position": 6,
          "points": 1190
        },
        {
          "cupId": 11,
          "position": 6,
          "points": 1420
        },
        {
          "cupId": 12,
          "position": 1,
          "points": 1420
        },
        {
          "cupId": 13,
          "position": 5,
          "points": 1390
        },
        {
          "cupId": 14,
          "position": 3,
          "points": 1420
        },
        {
          "cupId": 15,
          "position": 8,
          "points": 770
        },
        {
          "cupId": 16,
          "position": 5,
          "points": 1410
        },
        {
          "cupId": 17,
          "position": 5,
          "points": 1340
        },
        {
          "cupId": 18,
          "position": 6,
          "points": 1250
        },
        {
          "cupId": 19,
          "position": 7,
          "points": 1420
        },
        {
          "cupId": 22,
          "position": 6,
          "points": 1154
        },
        {
          "cupId": 23,
          "position": 7,
          "points": 1317
        },
        {
          "cupId": 24,
          "position": 8,
          "points": 1340
        },
        {
          "cupId": 25,
          "position": 5,
          "points": 1420
        }
      ]
    },
    "DENNY_SIUS": {
      "name": "DENNY_SIUS",
      "clubTag": "BYTE",
      "stats": {
        "totalPoints": 13890,
        "cupsPlayed": 11,
        "wins": 0,
        "podiums": 1,
        "avgPosition": 6.09,
        "bestPosition": 3,
        "worstPosition": 8
      },
      "bestTimes": [],
      "cupHistory": [
        {
          "cupId": 1,
          "position": 8,
          "points": 1180
        },
        {
          "cupId": 3,
          "position": 6,
          "points": 1200
        },
        {
          "cupId": 5,
          "position": 6,
          "points": 1300
        },
        {
          "cupId": 7,
          "position": 7,
          "points": 1120
        },
        {
          "cupId": 8,
          "position": 8,
          "points": 1190
        },
        {
          "cupId": 9,
          "position": 5,
          "points": 1150
        },
        {
          "cupId": 11,
          "position": 7,
          "points": 1280
        },
        {
          "cupId": 12,
          "position": 6,
          "points": 1210
        },
        {
          "cupId": 13,
          "position": 3,
          "points": 1420
        },
        {
          "cupId": 14,
          "position": 5,
          "points": 1420
        },
        {
          "cupId": 19,
          "position": 6,
          "points": 1420
        }
      ]
    },
    "PUTZERFISCH187": {
      "name": "PUTZERFISCH187",
      "clubTag": "STWA",
      "stats": {
        "totalPoints": 16895,
        "cupsPlayed": 21,
        "wins": 0,
        "podiums": 0,
        "avgPosition": 9.48,
        "bestPosition": 6,
        "worstPosition": 16
      },
      "bestTimes": [],
      "cupHistory": [
        {
          "cupId": 1,
          "position": 9,
          "points": 1070
        },
        {
          "cupId": 2,
          "position": 9,
          "points": 940
        },
        {
          "cupId": 5,
          "position": 9,
          "points": 990
        },
        {
          "cupId": 7,
          "position": 9,
          "points": 780
        },
        {
          "cupId": 8,
          "position": 7,
          "points": 1270
        },
        {
          "cupId": 9,
          "position": 8,
          "points": 770
        },
        {
          "cupId": 10,
          "position": 7,
          "points": 900
        },
        {
          "cupId": 11,
          "position": 8,
          "points": 830
        },
        {
          "cupId": 12,
          "position": 8,
          "points": 460
        },
        {
          "cupId": 13,
          "position": 8,
          "points": 740
        },
        {
          "cupId": 14,
          "position": 11,
          "points": 380
        },
        {
          "cupId": 15,
          "position": 9,
          "points": 680
        },
        {
          "cupId": 16,
          "position": 6,
          "points": 1160
        },
        {
          "cupId": 17,
          "position": 8,
          "points": 900
        },
        {
          "cupId": 19,
          "position": 9,
          "points": 975
        },
        {
          "cupId": 20,
          "position": 7,
          "points": 1345
        },
        {
          "cupId": 21,
          "position": 9,
          "points": 994
        },
        {
          "cupId": 22,
          "position": 14,
          "points": 381
        },
        {
          "cupId": 23,
          "position": 16,
          "points": 551
        },
        {
          "cupId": 24,
          "position": 15,
          "points": 54
        },
        {
          "cupId": 25,
          "position": 13,
          "points": 725
        }
      ]
    },
    "TRIXICAT": {
      "name": "TRIXICAT",
      "clubTag": "STWA",
      "stats": {
        "totalPoints": 4839,
        "cupsPlayed": 6,
        "wins": 0,
        "podiums": 0,
        "avgPosition": 10.33,
        "bestPosition": 6,
        "worstPosition": 16
      },
      "bestTimes": [],
      "cupHistory": [
        {
          "cupId": 1,
          "position": 10,
          "points": 950
        },
        {
          "cupId": 2,
          "position": 7,
          "points": 1180
        },
        {
          "cupId": 9,
          "position": 6,
          "points": 1070
        },
        {
          "cupId": 23,
          "position": 14,
          "points": 615
        },
        {
          "cupId": 24,
          "position": 16,
          "points": 50
        },
        {
          "cupId": 25,
          "position": 9,
          "points": 974
        }
      ]
    },
    "TT-BASTI": {
      "name": "TT-BASTI",
      "clubTag": "STWA",
      "stats": {
        "totalPoints": 2870,
        "cupsPlayed": 3,
        "wins": 0,
        "podiums": 2,
        "avgPosition": 6,
        "bestPosition": 2,
        "worstPosition": 13
      },
      "bestTimes": [
        {
          "cupId": 3,
          "time": "0:50.894",
          "date": "13.11.2024"
        }
      ],
      "cupHistory": [
        {
          "cupId": 2,
          "position": 2,
          "points": 1420
        },
        {
          "cupId": 3,
          "position": 3,
          "points": 1420
        },
        {
          "cupId": 17,
          "position": 13,
          "points": 30
        }
      ]
    },
    "SAAIJROO": {
      "name": "SAAIJROO",
      "clubTag": "STWA",
      "stats": {
        "totalPoints": 3213,
        "cupsPlayed": 4,
        "wins": 0,
        "podiums": 0,
        "avgPosition": 9.25,
        "bestPosition": 5,
        "worstPosition": 15
      },
      "bestTimes": [],
      "cupHistory": [
        {
          "cupId": 2,
          "position": 5,
          "points": 1380
        },
        {
          "cupId": 12,
          "position": 5,
          "points": 1350
        },
        {
          "cupId": 21,
          "position": 12,
          "points": 430
        },
        {
          "cupId": 22,
          "position": 15,
          "points": 53
        }
      ]
    },
    "TORBEN.TM": {
      "name": "TORBEN.TM",
      "clubTag": "STWA",
      "stats": {
        "totalPoints": 1420,
        "cupsPlayed": 1,
        "wins": 1,
        "podiums": 1,
        "avgPosition": 1,
        "bestPosition": 1,
        "worstPosition": 1
      },
      "bestTimes": [],
      "cupHistory": [
        {
          "cupId": 3,
          "position": 1,
          "points": 1420
        }
      ]
    },
    "REALEPIPHANY": {
      "name": "REALEPIPHANY",
      "clubTag": "MEOW",
      "stats": {
        "totalPoints": 21280,
        "cupsPlayed": 15,
        "wins": 9,
        "podiums": 14,
        "avgPosition": 1.6,
        "bestPosition": 1,
        "worstPosition": 4
      },
      "bestTimes": [
        {
          "cupId": 4,
          "time": "0:42.448",
          "date": "20.11.2024"
        },
        {
          "cupId": 7,
          "time": "0:43.938",
          "date": "11.12.2024"
        },
        {
          "cupId": 13,
          "time": "0:38.885",
          "date": "22.01.2025"
        },
        {
          "cupId": 19,
          "time": "0:43.995",
          "date": "18.02.2026"
        },
        {
          "cupId": 20,
          "time": "0:43.740",
          "date": "25.02.2026"
        },
        {
          "cupId": 21,
          "time": "0:48.378",
          "date": "11.03.2026"
        },
        {
          "cupId": 22,
          "time": "0:35.050",
          "date": "18.03.2026"
        },
        {
          "cupId": 24,
          "time": "0:42.280",
          "date": "01.04.2026"
        },
        {
          "cupId": 25,
          "time": "0:41.724",
          "date": "08.04.2026"
        }
      ],
      "cupHistory": [
        {
          "cupId": 3,
          "position": 2,
          "points": 1420
        },
        {
          "cupId": 4,
          "position": 1,
          "points": 1420
        },
        {
          "cupId": 7,
          "position": 1,
          "points": 1420
        },
        {
          "cupId": 8,
          "position": 2,
          "points": 1420
        },
        {
          "cupId": 13,
          "position": 1,
          "points": 1420
        },
        {
          "cupId": 14,
          "position": 2,
          "points": 1420
        },
        {
          "cupId": 17,
          "position": 4,
          "points": 1400
        },
        {
          "cupId": 18,
          "position": 3,
          "points": 1420
        },
        {
          "cupId": 19,
          "position": 1,
          "points": 1420
        },
        {
          "cupId": 20,
          "position": 1,
          "points": 1420
        },
        {
          "cupId": 21,
          "position": 2,
          "points": 1420
        },
        {
          "cupId": 22,
          "position": 1,
          "points": 1420
        },
        {
          "cupId": 23,
          "position": 1,
          "points": 1420
        },
        {
          "cupId": 24,
          "position": 1,
          "points": 1420
        },
        {
          "cupId": 25,
          "position": 1,
          "points": 1420
        }
      ]
    },
    "GOLDTIME.": {
      "name": "GOLDTIME.",
      "clubTag": "BYTE",
      "stats": {
        "totalPoints": 1390,
        "cupsPlayed": 1,
        "wins": 0,
        "podiums": 0,
        "avgPosition": 4,
        "bestPosition": 4,
        "worstPosition": 4
      },
      "bestTimes": [],
      "cupHistory": [
        {
          "cupId": 3,
          "position": 4,
          "points": 1390
        }
      ]
    },
    "SAPIHR": {
      "name": "SAPIHR",
      "clubTag": "BYTE",
      "stats": {
        "totalPoints": 960,
        "cupsPlayed": 1,
        "wins": 0,
        "podiums": 0,
        "avgPosition": 9,
        "bestPosition": 9,
        "worstPosition": 9
      },
      "bestTimes": [],
      "cupHistory": [
        {
          "cupId": 3,
          "position": 9,
          "points": 960
        }
      ]
    },
    "JJURIJJ": {
      "name": "JJURIJJ",
      "clubTag": "BYTE",
      "stats": {
        "totalPoints": 6250,
        "cupsPlayed": 7,
        "wins": 0,
        "podiums": 0,
        "avgPosition": 8.14,
        "bestPosition": 4,
        "worstPosition": 12
      },
      "bestTimes": [],
      "cupHistory": [
        {
          "cupId": 4,
          "position": 7,
          "points": 1100
        },
        {
          "cupId": 11,
          "position": 4,
          "points": 1420
        },
        {
          "cupId": 14,
          "position": 8,
          "points": 720
        },
        {
          "cupId": 15,
          "position": 7,
          "points": 860
        },
        {
          "cupId": 17,
          "position": 11,
          "points": 230
        },
        {
          "cupId": 19,
          "position": 8,
          "points": 985
        },
        {
          "cupId": 20,
          "position": 12,
          "points": 935
        }
      ]
    },
    "ZERBREZLER2000": {
      "name": "ZERBREZLER2000",
      "clubTag": "BYTE",
      "stats": {
        "totalPoints": 8520,
        "cupsPlayed": 6,
        "wins": 2,
        "podiums": 4,
        "avgPosition": 2.67,
        "bestPosition": 1,
        "worstPosition": 6
      },
      "bestTimes": [
        {
          "cupId": 5,
          "time": "0:40.062",
          "date": "27.11.2024"
        }
      ],
      "cupHistory": [
        {
          "cupId": 5,
          "position": 1,
          "points": 1420
        },
        {
          "cupId": 7,
          "position": 2,
          "points": 1420
        },
        {
          "cupId": 20,
          "position": 4,
          "points": 1420
        },
        {
          "cupId": 21,
          "position": 1,
          "points": 1420
        },
        {
          "cupId": 23,
          "position": 6,
          "points": 1420
        },
        {
          "cupId": 24,
          "position": 2,
          "points": 1420
        }
      ]
    },
    "FRANKFURT.HBF": {
      "name": "FRANKFURT.HBF",
      "clubTag": "FFM",
      "stats": {
        "totalPoints": 21174,
        "cupsPlayed": 15,
        "wins": 3,
        "podiums": 12,
        "avgPosition": 2.67,
        "bestPosition": 1,
        "worstPosition": 5
      },
      "bestTimes": [
        {
          "cupId": 8,
          "time": "0:13.490",
          "date": "18.12.2024"
        },
        {
          "cupId": 11,
          "time": "0:44.792",
          "date": "08.01.2025"
        },
        {
          "cupId": 17,
          "time": "0:47.335",
          "date": "04.02.2026"
        }
      ],
      "cupHistory": [
        {
          "cupId": 7,
          "position": 3,
          "points": 1420
        },
        {
          "cupId": 8,
          "position": 3,
          "points": 1420
        },
        {
          "cupId": 9,
          "position": 1,
          "points": 1420
        },
        {
          "cupId": 10,
          "position": 3,
          "points": 1420
        },
        {
          "cupId": 11,
          "position": 1,
          "points": 1420
        },
        {
          "cupId": 12,
          "position": 3,
          "points": 1420
        },
        {
          "cupId": 14,
          "position": 4,
          "points": 1420
        },
        {
          "cupId": 15,
          "position": 5,
          "points": 1410
        },
        {
          "cupId": 16,
          "position": 1,
          "points": 1420
        },
        {
          "cupId": 17,
          "position": 2,
          "points": 1420
        },
        {
          "cupId": 20,
          "position": 2,
          "points": 1420
        },
        {
          "cupId": 21,
          "position": 3,
          "points": 1420
        },
        {
          "cupId": 22,
          "position": 4,
          "points": 1304
        },
        {
          "cupId": 23,
          "position": 2,
          "points": 1420
        },
        {
          "cupId": 25,
          "position": 3,
          "points": 1420
        }
      ]
    },
    "MC_DELLA": {
      "name": "MC_DELLA",
      "clubTag": "BYTE",
      "stats": {
        "totalPoints": 1330,
        "cupsPlayed": 3,
        "wins": 0,
        "podiums": 0,
        "avgPosition": 8.67,
        "bestPosition": 7,
        "worstPosition": 10
      },
      "bestTimes": [],
      "cupHistory": [
        {
          "cupId": 11,
          "position": 9,
          "points": 440
        },
        {
          "cupId": 12,
          "position": 7,
          "points": 470
        },
        {
          "cupId": 17,
          "position": 10,
          "points": 420
        }
      ]
    },
    "EVI_420": {
      "name": "EVI_420",
      "clubTag": "BYTE",
      "stats": {
        "totalPoints": 4260,
        "cupsPlayed": 3,
        "wins": 0,
        "podiums": 1,
        "avgPosition": 3.33,
        "bestPosition": 2,
        "worstPosition": 4
      },
      "bestTimes": [],
      "cupHistory": [
        {
          "cupId": 12,
          "position": 4,
          "points": 1420
        },
        {
          "cupId": 15,
          "position": 2,
          "points": 1420
        },
        {
          "cupId": 21,
          "position": 4,
          "points": 1420
        }
      ]
    },
    "OXIRT": {
      "name": "OXIRT",
      "clubTag": "BYTE",
      "stats": {
        "totalPoints": 5094,
        "cupsPlayed": 5,
        "wins": 0,
        "podiums": 0,
        "avgPosition": 8.8,
        "bestPosition": 6,
        "worstPosition": 11
      },
      "bestTimes": [],
      "cupHistory": [
        {
          "cupId": 14,
          "position": 7,
          "points": 990
        },
        {
          "cupId": 20,
          "position": 11,
          "points": 1105
        },
        {
          "cupId": 22,
          "position": 11,
          "points": 645
        },
        {
          "cupId": 23,
          "position": 9,
          "points": 1061
        },
        {
          "cupId": 25,
          "position": 6,
          "points": 1293
        }
      ]
    },
    "WALLHATER": {
      "name": "WALLHATER",
      "clubTag": "FWMC",
      "stats": {
        "totalPoints": 7789,
        "cupsPlayed": 9,
        "wins": 0,
        "podiums": 0,
        "avgPosition": 9.89,
        "bestPosition": 7,
        "worstPosition": 13
      },
      "bestTimes": [],
      "cupHistory": [
        {
          "cupId": 14,
          "position": 10,
          "points": 490
        },
        {
          "cupId": 17,
          "position": 9,
          "points": 690
        },
        {
          "cupId": 19,
          "position": 10,
          "points": 835
        },
        {
          "cupId": 20,
          "position": 10,
          "points": 1150
        },
        {
          "cupId": 21,
          "position": 7,
          "points": 1113
        },
        {
          "cupId": 22,
          "position": 13,
          "points": 461
        },
        {
          "cupId": 23,
          "position": 10,
          "points": 1028
        },
        {
          "cupId": 24,
          "position": 9,
          "points": 1145
        },
        {
          "cupId": 25,
          "position": 11,
          "points": 877
        }
      ]
    },
    "ITSARTCORE": {
      "name": "ITSARTCORE",
      "clubTag": "CS",
      "stats": {
        "totalPoints": 1230,
        "cupsPlayed": 1,
        "wins": 0,
        "podiums": 0,
        "avgPosition": 6,
        "bestPosition": 6,
        "worstPosition": 6
      },
      "bestTimes": [],
      "cupHistory": [
        {
          "cupId": 15,
          "position": 6,
          "points": 1230
        }
      ]
    },
    "RACACAX": {
      "name": "RACACAX",
      "clubTag": "EKMEK",
      "stats": {
        "totalPoints": 2840,
        "cupsPlayed": 2,
        "wins": 0,
        "podiums": 2,
        "avgPosition": 3,
        "bestPosition": 3,
        "worstPosition": 3
      },
      "bestTimes": [],
      "cupHistory": [
        {
          "cupId": 17,
          "position": 3,
          "points": 1420
        },
        {
          "cupId": 22,
          "position": 3,
          "points": 1420
        }
      ]
    },
    "JUERGEN.TM": {
      "name": "JUERGEN.TM",
      "clubTag": "BYTE",
      "stats": {
        "totalPoints": 2680,
        "cupsPlayed": 2,
        "wins": 0,
        "podiums": 1,
        "avgPosition": 5,
        "bestPosition": 2,
        "worstPosition": 8
      },
      "bestTimes": [
        {
          "cupId": 18,
          "time": "0:39.455",
          "date": "19.02.2026"
        }
      ],
      "cupHistory": [
        {
          "cupId": 18,
          "position": 2,
          "points": 1420
        },
        {
          "cupId": 20,
          "position": 8,
          "points": 1260
        }
      ]
    },
    "MEFPEFZEF": {
      "name": "MEFPEFZEF",
      "clubTag": "BYTE",
      "stats": {
        "totalPoints": 5390,
        "cupsPlayed": 6,
        "wins": 0,
        "podiums": 0,
        "avgPosition": 9.17,
        "bestPosition": 5,
        "worstPosition": 11
      },
      "bestTimes": [],
      "cupHistory": [
        {
          "cupId": 19,
          "position": 11,
          "points": 735
        },
        {
          "cupId": 20,
          "position": 9,
          "points": 1235
        },
        {
          "cupId": 21,
          "position": 5,
          "points": 1270
        },
        {
          "cupId": 22,
          "position": 10,
          "points": 667
        },
        {
          "cupId": 24,
          "position": 10,
          "points": 520
        },
        {
          "cupId": 25,
          "position": 10,
          "points": 963
        }
      ]
    },
    "HUGINRABE": {
      "name": "HUGINRABE",
      "clubTag": "H-ET",
      "stats": {
        "totalPoints": 640,
        "cupsPlayed": 1,
        "wins": 0,
        "podiums": 0,
        "avgPosition": 13,
        "bestPosition": 13,
        "worstPosition": 13
      },
      "bestTimes": [],
      "cupHistory": [
        {
          "cupId": 20,
          "position": 13,
          "points": 640
        }
      ]
    },
    "OUTYTM": {
      "name": "OUTYTM",
      "clubTag": "STWA",
      "stats": {
        "totalPoints": 975,
        "cupsPlayed": 3,
        "wins": 0,
        "podiums": 0,
        "avgPosition": 14.33,
        "bestPosition": 11,
        "worstPosition": 18
      },
      "bestTimes": [],
      "cupHistory": [
        {
          "cupId": 21,
          "position": 11,
          "points": 565
        },
        {
          "cupId": 24,
          "position": 18,
          "points": 8
        },
        {
          "cupId": 25,
          "position": 14,
          "points": 402
        }
      ]
    },
    "ISHOWFULLSPEED": {
      "name": "ISHOWFULLSPEED",
      "clubTag": "NN",
      "stats": {
        "totalPoints": 566,
        "cupsPlayed": 1,
        "wins": 0,
        "podiums": 0,
        "avgPosition": 12,
        "bestPosition": 12,
        "worstPosition": 12
      },
      "bestTimes": [],
      "cupHistory": [
        {
          "cupId": 22,
          "position": 12,
          "points": 566
        }
      ]
    },
    "SCEPTICHAMSTER": {
      "name": "SCEPTICHAMSTER",
      "clubTag": "BYTE",
      "stats": {
        "totalPoints": 2835,
        "cupsPlayed": 2,
        "wins": 0,
        "podiums": 1,
        "avgPosition": 5,
        "bestPosition": 3,
        "worstPosition": 7
      },
      "bestTimes": [],
      "cupHistory": [
        {
          "cupId": 23,
          "position": 3,
          "points": 1420
        },
        {
          "cupId": 24,
          "position": 7,
          "points": 1415
        }
      ]
    },
    "ZAZURIN": {
      "name": "ZAZURIN",
      "clubTag": "BYTE",
      "stats": {
        "totalPoints": 1461,
        "cupsPlayed": 2,
        "wins": 0,
        "podiums": 0,
        "avgPosition": 9.5,
        "bestPosition": 8,
        "worstPosition": 11
      },
      "bestTimes": [],
      "cupHistory": [
        {
          "cupId": 23,
          "position": 8,
          "points": 1070
        },
        {
          "cupId": 24,
          "position": 11,
          "points": 391
        }
      ]
    },
    "RUDY._.TM": {
      "name": "RUDY._.TM",
      "clubTag": "STWA",
      "stats": {
        "totalPoints": 1848,
        "cupsPlayed": 2,
        "wins": 0,
        "podiums": 0,
        "avgPosition": 11.5,
        "bestPosition": 11,
        "worstPosition": 12
      },
      "bestTimes": [],
      "cupHistory": [
        {
          "cupId": 23,
          "position": 11,
          "points": 1020
        },
        {
          "cupId": 25,
          "position": 12,
          "points": 828
        }
      ]
    },
    "APOTM2": {
      "name": "APOTM2",
      "clubTag": "EVP",
      "stats": {
        "totalPoints": 731,
        "cupsPlayed": 1,
        "wins": 0,
        "podiums": 0,
        "avgPosition": 13,
        "bestPosition": 13,
        "worstPosition": 13
      },
      "bestTimes": [],
      "cupHistory": [
        {
          "cupId": 23,
          "position": 13,
          "points": 731
        }
      ]
    },
    "SHIQQY420": {
      "name": "SHIQQY420",
      "clubTag": "STWA",
      "stats": {
        "totalPoints": 567,
        "cupsPlayed": 1,
        "wins": 0,
        "podiums": 0,
        "avgPosition": 15,
        "bestPosition": 15,
        "worstPosition": 15
      },
      "bestTimes": [],
      "cupHistory": [
        {
          "cupId": 23,
          "position": 15,
          "points": 567
        }
      ]
    },
    "MONTI_91": {
      "name": "MONTI_91",
      "clubTag": "BYTE",
      "stats": {
        "totalPoints": 1420,
        "cupsPlayed": 1,
        "wins": 0,
        "podiums": 0,
        "avgPosition": 6,
        "bestPosition": 6,
        "worstPosition": 6
      },
      "bestTimes": [],
      "cupHistory": [
        {
          "cupId": 24,
          "position": 6,
          "points": 1420
        }
      ]
    },
    "JOTHAN518": {
      "name": "JOTHAN518",
      "clubTag": "--",
      "stats": {
        "totalPoints": 276,
        "cupsPlayed": 1,
        "wins": 0,
        "podiums": 0,
        "avgPosition": 12,
        "bestPosition": 12,
        "worstPosition": 12
      },
      "bestTimes": [],
      "cupHistory": [
        {
          "cupId": 24,
          "position": 12,
          "points": 276
        }
      ]
    },
    "C1UMSYSSLOTH": {
      "name": "C1UMSYSSLOTH",
      "clubTag": "--",
      "stats": {
        "totalPoints": 252,
        "cupsPlayed": 1,
        "wins": 0,
        "podiums": 0,
        "avgPosition": 13,
        "bestPosition": 13,
        "worstPosition": 13
      },
      "bestTimes": [],
      "cupHistory": [
        {
          "cupId": 24,
          "position": 13,
          "points": 252
        }
      ]
    }
  },
  "meta": {
    "lastUpdated": "2026-04-15",
    "totalPlayers": 38,
    "totalCups": 24
  }
}